<?xml version="1.0" encoding="utf-8"?>
<Dependencies>
  <Source Uri="https://github.com/dotnet/dotnet" Mapping="arcade" Sha="8b29a1682219da555ee27e4fdda55dc3884b316f" BarId="277635" />
  <ProductDependencies>
  </ProductDependencies>
  <ToolsetDependencies>
    <Dependency Name="Microsoft.DotNet.Arcade.Sdk" Version="10.0.0-beta.25422.3">
      <Uri>https://github.com/dotnet/arcade</Uri>
      <Sha>f2cdf946c00a12a2c283835bb41ddc2255832055</Sha>
    </Dependency>
  </ToolsetDependencies>
</Dependencies>
